ts2d/__init__.py
ts2d/__main__.py
ts2d/main.py
ts2d/tool.py
ts2d/core/__init__.py
ts2d/core/inference/__init__.py
ts2d/core/inference/database.py
ts2d/core/inference/nnu.py
ts2d/core/inference/prediction_worker.py
ts2d/core/inference/predictor.py
ts2d/core/inference/wrapper.py
ts2d/core/inference/zoo.py
ts2d/core/util/__init__.py
ts2d/core/util/color.py
ts2d/core/util/config.py
ts2d/core/util/file.py
ts2d/core/util/image.py
ts2d/core/util/log.py
ts2d/core/util/meta.py
ts2d/core/util/path.py
ts2d/core/util/sitk_util.py
ts2d/core/util/temp.py
ts2d/core/util/types.py
ts2d/core/util/util.py
ts2d/data/config.json
ts2d/data/label-colors.csv
ts2d/data/shared.json
ts2d-1.2.0.dist-info/licenses/LICENSE
ts2d-1.2.0.dist-info/METADATA
ts2d-1.2.0.dist-info/WHEEL
ts2d-1.2.0.dist-info/entry_points.txt
ts2d-1.2.0.dist-info/top_level.txt
ts2d-1.2.0.dist-info/RECORD
