Metadata-Version: 2.4
Name: ts2d
Version: 1.2.0
Summary: A tool for rapid anatomical structure detection and analysis.
Author-email: bsabrows <bertram.sabrowsky-hirsch@risc-software.at>
License-Expression: Apache-2.0
Project-URL: Homepage, https://github.com/risc-mi/totalsegmentator2D
Classifier: Intended Audience :: Science/Research
Classifier: Topic :: Scientific/Engineering :: Image Processing
Classifier: Topic :: Scientific/Engineering :: Medical Science Apps.
Classifier: Programming Language :: Python :: 3
Classifier: Operating System :: OS Independent
Requires-Python: >=3.12
License-File: LICENSE
Requires-Dist: torch~=2.7.0
Requires-Dist: torchvision
Requires-Dist: torchaudio
Requires-Dist: simpleitk~=2.5.2
Requires-Dist: pandas~=2.3.1
Requires-Dist: gdown~=5.2.0
Requires-Dist: psutil~=7.0
Requires-Dist: nnunetv2ml==2.6.2
Provides-Extra: test
Requires-Dist: pytest; extra == "test"
Dynamic: license-file
